Metadata-Version: 2.1
Name: beautider
Version: 0.1.5
Summary: Module for creating progress bars.
Home-page: https://github.com/bolgaro4ka
Author: bolgaro4ka
Author-email: bolgaro4ka.github@gmail.com
Project-URL: GitHub, https://github.com/bolgaro4ka
Keywords: progress bar
Classifier: Programming Language :: Python :: 3.10
Classifier: License :: OSI Approved :: MIT License
Classifier: Operating System :: OS Independent
Requires-Python: >=3.8
